{
    "directed": false,
    "graph": {
        "name": "compose( ,  )"
    },
    "links": [
        {
            "source": "http://vivo.brown.edu/individual/jhogansc",
            "target": "http://vivo.brown.edu/individual/xl6",
            "weight": 1
        },
        {
            "source": "http://vivo.brown.edu/individual/jhogansc",
            "target": "http://vivo.brown.edu/individual/jkurtis",
            "weight": 1
        },
        {
            "source": "http://vivo.brown.edu/individual/jhogansc",
            "target": "http://vivo.brown.edu/individual/rpapas",
            "weight": 1
        },
        {
            "source": "http://vivo.brown.edu/individual/jhogansc",
            "target": "http://vivo.brown.edu/individual/zjwu",
            "weight": 1
        },
        {
            "source": "http://vivo.brown.edu/individual/jhogansc",
            "target": "http://vivo.brown.edu/individual/sbuka",
            "weight": 3
        },
        {
            "source": "http://vivo.brown.edu/individual/jhogansc",
            "target": "http://vivo.brown.edu/individual/ceatonmd",
            "weight": 2
        },
        {
            "source": "http://vivo.brown.edu/individual/jhogansc",
            "target": "http://vivo.brown.edu/individual/suvinmd",
            "weight": 7
        },
        {
            "source": "http://vivo.brown.edu/individual/jhogansc",
            "target": "http://vivo.brown.edu/individual/wrakowsk",
            "weight": 1
        },
        {
            "source": "http://vivo.brown.edu/individual/jhogansc",
            "target": "http://vivo.brown.edu/individual/fgillani",
            "weight": 1
        },
        {
            "source": "http://vivo.brown.edu/individual/jhogansc",
            "target": "http://vivo.brown.edu/individual/sallen",
            "weight": 1
        },
        {
            "source": "http://vivo.brown.edu/individual/jhogansc",
            "target": "http://vivo.brown.edu/individual/smcgarve",
            "weight": 1
        },
        {
            "source": "http://vivo.brown.edu/individual/jhogansc",
            "target": "http://vivo.brown.edu/individual/bgenberg",
            "weight": 2
        },
        {
            "source": "http://vivo.brown.edu/individual/jhogansc",
            "target": "http://vivo.brown.edu/individual/tl7",
            "weight": 3
        },
        {
            "source": "http://vivo.brown.edu/individual/jhogansc",
            "target": "http://vivo.brown.edu/individual/jffriedm",
            "weight": 1
        },
        {
            "source": "http://vivo.brown.edu/individual/jhogansc",
            "target": "http://vivo.brown.edu/individual/rcmercha",
            "weight": 1
        },
        {
            "source": "http://vivo.brown.edu/individual/jhogansc",
            "target": "http://vivo.brown.edu/individual/vmor",
            "weight": 1
        },
        {
            "source": "http://vivo.brown.edu/individual/jhogansc",
            "target": "http://vivo.brown.edu/individual/nbarnett",
            "weight": 1
        },
        {
            "source": "http://vivo.brown.edu/individual/jhogansc",
            "target": "http://vivo.brown.edu/individual/ejcarter",
            "weight": 1
        },
        {
            "source": "http://vivo.brown.edu/individual/jhogansc",
            "target": "http://vivo.brown.edu/individual/jrichmph",
            "weight": 2
        },
        {
            "source": "http://vivo.brown.edu/individual/jhogansc",
            "target": "http://vivo.brown.edu/individual/rkantor",
            "weight": 8
        },
        {
            "source": "http://vivo.brown.edu/individual/jhogansc",
            "target": "http://vivo.brown.edu/individual/dmwillia",
            "weight": 1
        },
        {
            "source": "http://vivo.brown.edu/individual/jhogansc",
            "target": "http://vivo.brown.edu/individual/bbockphd",
            "weight": 4
        },
        {
            "source": "http://vivo.brown.edu/individual/mlurieph",
            "target": "http://vivo.brown.edu/individual/smcgarve",
            "weight": 7
        },
        {
            "source": "http://vivo.brown.edu/individual/jkurtis",
            "target": "http://vivo.brown.edu/individual/imichelo",
            "weight": 1
        },
        {
            "source": "http://vivo.brown.edu/individual/jkurtis",
            "target": "http://vivo.brown.edu/individual/jpadbury",
            "weight": 1
        },
        {
            "source": "http://vivo.brown.edu/individual/jkurtis",
            "target": "http://vivo.brown.edu/individual/jffriedm",
            "weight": 34
        },
        {
            "source": "http://vivo.brown.edu/individual/jkurtis",
            "target": "http://vivo.brown.edu/individual/cnixon",
            "weight": 4
        },
        {
            "source": "http://vivo.brown.edu/individual/jkurtis",
            "target": "http://vivo.brown.edu/individual/smcgarve",
            "weight": 24
        },
        {
            "source": "http://vivo.brown.edu/individual/jkurtis",
            "target": "http://vivo.brown.edu/individual/vmor",
            "weight": 2
        },
        {
            "source": "http://vivo.brown.edu/individual/jkurtis",
            "target": "http://vivo.brown.edu/individual/draj1",
            "weight": 1
        },
        {
            "source": "http://vivo.brown.edu/individual/jkurtis",
            "target": "http://vivo.brown.edu/individual/fgundoga",
            "weight": 3
        },
        {
            "source": "http://vivo.brown.edu/individual/jusanche",
            "target": "http://vivo.brown.edu/individual/jpadbury",
            "weight": 1
        },
        {
            "source": "http://vivo.brown.edu/individual/asbrodsk",
            "target": "http://vivo.brown.edu/individual/jpadbury",
            "weight": 1
        },
        {
            "source": "http://vivo.brown.edu/individual/jaliotta",
            "target": "http://vivo.brown.edu/individual/jpadbury",
            "weight": 1
        },
        {
            "source": "http://vivo.brown.edu/individual/jwandsmd",
            "target": "http://vivo.brown.edu/individual/fgundoga",
            "weight": 2
        },
        {
            "source": "http://vivo.brown.edu/individual/zfeng",
            "target": "http://vivo.brown.edu/individual/vmor",
            "weight": 39
        },
        {
            "source": "http://vivo.brown.edu/individual/ceatonmd",
            "target": "http://vivo.brown.edu/individual/vmor",
            "weight": 2
        },
        {
            "source": "http://vivo.brown.edu/individual/kst",
            "target": "http://vivo.brown.edu/individual/vmor",
            "weight": 12
        },
        {
            "source": "http://vivo.brown.edu/individual/suvinmd",
            "target": "http://vivo.brown.edu/individual/smcgarve",
            "weight": 2
        },
        {
            "source": "http://vivo.brown.edu/individual/wrakowsk",
            "target": "http://vivo.brown.edu/individual/vmor",
            "weight": 2
        },
        {
            "source": "http://vivo.brown.edu/individual/ddore",
            "target": "http://vivo.brown.edu/individual/vmor",
            "weight": 8
        },
        {
            "source": "http://vivo.brown.edu/individual/bm8",
            "target": "http://vivo.brown.edu/individual/smcgarve",
            "weight": 1
        },
        {
            "source": "http://vivo.brown.edu/individual/sallen",
            "target": "http://vivo.brown.edu/individual/vmor",
            "weight": 3
        },
        {
            "source": "http://vivo.brown.edu/individual/gwelleni",
            "target": "http://vivo.brown.edu/individual/vmor",
            "weight": 1
        },
        {
            "source": "http://vivo.brown.edu/individual/smcgarve",
            "target": "http://vivo.brown.edu/individual/zjwu",
            "weight": 2
        },
        {
            "source": "http://vivo.brown.edu/individual/smcgarve",
            "target": "http://vivo.brown.edu/individual/aspirito",
            "weight": 1
        },
        {
            "source": "http://vivo.brown.edu/individual/smcgarve",
            "target": "http://vivo.brown.edu/individual/jffriedm",
            "weight": 22
        },
        {
            "source": "http://vivo.brown.edu/individual/smcgarve",
            "target": "http://vivo.brown.edu/individual/dcoustan",
            "weight": 3
        },
        {
            "source": "http://vivo.brown.edu/individual/smcgarve",
            "target": "http://vivo.brown.edu/individual/miwhite",
            "weight": 1
        },
        {
            "source": "http://vivo.brown.edu/individual/smcgarve",
            "target": "http://vivo.brown.edu/individual/agjelsvi",
            "weight": 4
        },
        {
            "source": "http://vivo.brown.edu/individual/smcgarve",
            "target": "http://vivo.brown.edu/individual/ktkelsey",
            "weight": 1
        },
        {
            "source": "http://vivo.brown.edu/individual/smcgarve",
            "target": "http://vivo.brown.edu/individual/rswiftmd",
            "weight": 1
        },
        {
            "source": "http://vivo.brown.edu/individual/smcgarve",
            "target": "http://vivo.brown.edu/individual/gpalomak",
            "weight": 1
        },
        {
            "source": "http://vivo.brown.edu/individual/smcgarve",
            "target": "http://vivo.brown.edu/individual/eloucks",
            "weight": 3
        },
        {
            "source": "http://vivo.brown.edu/individual/smcgarve",
            "target": "http://vivo.brown.edu/individual/rrosen",
            "weight": 6
        },
        {
            "source": "http://vivo.brown.edu/individual/smcgarve",
            "target": "http://vivo.brown.edu/individual/ks18",
            "weight": 1
        },
        {
            "source": "http://vivo.brown.edu/individual/smcgarve",
            "target": "http://vivo.brown.edu/individual/cnixon",
            "weight": 1
        },
        {
            "source": "http://vivo.brown.edu/individual/smcgarve",
            "target": "http://vivo.brown.edu/individual/vmor",
            "weight": 2
        },
        {
            "source": "http://vivo.brown.edu/individual/auzun",
            "target": "http://vivo.brown.edu/individual/jpadbury",
            "weight": 13
        },
        {
            "source": "http://vivo.brown.edu/individual/atuya",
            "target": "http://vivo.brown.edu/individual/vmor",
            "weight": 2
        },
        {
            "source": "http://vivo.brown.edu/individual/smillerp",
            "target": "http://vivo.brown.edu/individual/vmor",
            "weight": 28
        },
        {
            "source": "http://vivo.brown.edu/individual/sc7",
            "target": "http://vivo.brown.edu/individual/jpadbury",
            "weight": 1
        },
        {
            "source": "http://vivo.brown.edu/individual/atrivedi",
            "target": "http://vivo.brown.edu/individual/vmor",
            "weight": 15
        },
        {
            "source": "http://vivo.brown.edu/individual/vknopik",
            "target": "http://vivo.brown.edu/individual/jpadbury",
            "weight": 1
        },
        {
            "source": "http://vivo.brown.edu/individual/lstroud",
            "target": "http://vivo.brown.edu/individual/jpadbury",
            "weight": 2
        },
        {
            "source": "http://vivo.brown.edu/individual/rg5",
            "target": "http://vivo.brown.edu/individual/vmor",
            "weight": 1
        },
        {
            "source": "http://vivo.brown.edu/individual/mvezerid",
            "target": "http://vivo.brown.edu/individual/vmor",
            "weight": 2
        },
        {
            "source": "http://vivo.brown.edu/individual/lresnikp",
            "target": "http://vivo.brown.edu/individual/vmor",
            "weight": 2
        },
        {
            "source": "http://vivo.brown.edu/individual/aayalaph",
            "target": "http://vivo.brown.edu/individual/jpadbury",
            "weight": 1
        },
        {
            "source": "http://vivo.brown.edu/individual/skostadi",
            "target": "http://vivo.brown.edu/individual/fgundoga",
            "weight": 3
        },
        {
            "source": "http://vivo.brown.edu/individual/skostadi",
            "target": "http://vivo.brown.edu/individual/jpadbury",
            "weight": 1
        },
        {
            "source": "http://vivo.brown.edu/individual/rbesdine",
            "target": "http://vivo.brown.edu/individual/vmor",
            "weight": 1
        },
        {
            "source": "http://vivo.brown.edu/individual/shaley",
            "target": "http://vivo.brown.edu/individual/jpadbury",
            "weight": 1
        },
        {
            "source": "http://vivo.brown.edu/individual/draj1",
            "target": "http://vivo.brown.edu/individual/jffriedm",
            "weight": 1
        },
        {
            "source": "http://vivo.brown.edu/individual/draj1",
            "target": "http://vivo.brown.edu/individual/cnixon",
            "weight": 1
        },
        {
            "source": "http://vivo.brown.edu/individual/draj1",
            "target": "http://vivo.brown.edu/individual/imichelo",
            "weight": 1
        },
        {
            "source": "http://vivo.brown.edu/individual/khawes",
            "target": "http://vivo.brown.edu/individual/jpadbury",
            "weight": 4
        },
        {
            "source": "http://vivo.brown.edu/individual/imichelo",
            "target": "http://vivo.brown.edu/individual/jffriedm",
            "weight": 1
        },
        {
            "source": "http://vivo.brown.edu/individual/imichelo",
            "target": "http://vivo.brown.edu/individual/cnixon",
            "weight": 1
        },
        {
            "source": "http://vivo.brown.edu/individual/imichelo",
            "target": "http://vivo.brown.edu/individual/jbliss",
            "weight": 1
        },
        {
            "source": "http://vivo.brown.edu/individual/fluksmd",
            "target": "http://vivo.brown.edu/individual/jpadbury",
            "weight": 1
        },
        {
            "source": "http://vivo.brown.edu/individual/gpapando",
            "target": "http://vivo.brown.edu/individual/vmor",
            "weight": 2
        },
        {
            "source": "http://vivo.brown.edu/individual/gpapando",
            "target": "http://vivo.brown.edu/individual/jpadbury",
            "weight": 3
        },
        {
            "source": "http://vivo.brown.edu/individual/fgundoga",
            "target": "http://vivo.brown.edu/individual/jffriedm",
            "weight": 3
        },
        {
            "source": "http://vivo.brown.edu/individual/fgundoga",
            "target": "http://vivo.brown.edu/individual/jbliss",
            "weight": 1
        },
        {
            "source": "http://vivo.brown.edu/individual/mfennell",
            "target": "http://vivo.brown.edu/individual/vmor",
            "weight": 8
        },
        {
            "source": "http://vivo.brown.edu/individual/ktkelsey",
            "target": "http://vivo.brown.edu/individual/jpadbury",
            "weight": 1
        },
        {
            "source": "http://vivo.brown.edu/individual/ogalarra",
            "target": "http://vivo.brown.edu/individual/vmor",
            "weight": 2
        },
        {
            "source": "http://vivo.brown.edu/individual/sbuka",
            "target": "http://vivo.brown.edu/individual/vmor",
            "weight": 2
        },
        {
            "source": "http://vivo.brown.edu/individual/rbaier",
            "target": "http://vivo.brown.edu/individual/vmor",
            "weight": 3
        },
        {
            "source": "http://vivo.brown.edu/individual/pgruppus",
            "target": "http://vivo.brown.edu/individual/jpadbury",
            "weight": 1
        },
        {
            "source": "http://vivo.brown.edu/individual/twetle",
            "target": "http://vivo.brown.edu/individual/vmor",
            "weight": 5
        },
        {
            "source": "http://vivo.brown.edu/individual/vmor",
            "target": "http://vivo.brown.edu/individual/nwardmd",
            "weight": 1
        },
        {
            "source": "http://vivo.brown.edu/individual/vmor",
            "target": "http://vivo.brown.edu/individual/iwilson",
            "weight": 1
        },
        {
            "source": "http://vivo.brown.edu/individual/vmor",
            "target": "http://vivo.brown.edu/individual/sgravens",
            "weight": 4
        },
        {
            "source": "http://vivo.brown.edu/individual/vmor",
            "target": "http://vivo.brown.edu/individual/jffriedm",
            "weight": 2
        },
        {
            "source": "http://vivo.brown.edu/individual/vmor",
            "target": "http://vivo.brown.edu/individual/wcwu",
            "weight": 2
        },
        {
            "source": "http://vivo.brown.edu/individual/vmor",
            "target": "http://vivo.brown.edu/individual/rnjones",
            "weight": 1
        },
        {
            "source": "http://vivo.brown.edu/individual/vmor",
            "target": "http://vivo.brown.edu/individual/pgozalo",
            "weight": 32
        },
        {
            "source": "http://vivo.brown.edu/individual/vmor",
            "target": "http://vivo.brown.edu/individual/rshieldp",
            "weight": 1
        },
        {
            "source": "http://vivo.brown.edu/individual/vmor",
            "target": "http://vivo.brown.edu/individual/mrahman",
            "weight": 8
        },
        {
            "source": "http://vivo.brown.edu/individual/vmor",
            "target": "http://vivo.brown.edu/individual/eamiller",
            "weight": 3
        },
        {
            "source": "http://vivo.brown.edu/individual/skshaw",
            "target": "http://vivo.brown.edu/individual/jpadbury",
            "weight": 2
        },
        {
            "source": "http://vivo.brown.edu/individual/cschorlp",
            "target": "http://vivo.brown.edu/individual/jpadbury",
            "weight": 1
        },
        {
            "source": "http://vivo.brown.edu/individual/bstonest",
            "target": "http://vivo.brown.edu/individual/jpadbury",
            "weight": 5
        },
        {
            "source": "http://vivo.brown.edu/individual/estopamd",
            "target": "http://vivo.brown.edu/individual/jpadbury",
            "weight": 1
        },
        {
            "source": "http://vivo.brown.edu/individual/jpadbury",
            "target": "http://vivo.brown.edu/individual/asalisbu",
            "weight": 4
        },
        {
            "source": "http://vivo.brown.edu/individual/jffriedm",
            "target": "http://vivo.brown.edu/individual/cnixon",
            "weight": 1
        }
    ],
    "multigraph": false,
    "nodes": [
        {
            "group": "Biostatistics",
            "id": "http://vivo.brown.edu/individual/jhogansc",
            "name": "Hogan, Joseph"
        },
        {
            "group": "Epidemiology",
            "id": "http://vivo.brown.edu/individual/mlurieph",
            "name": "Lurie, Mark"
        },
        {
            "group": "Pathology and Laboratory Medicine",
            "id": "http://vivo.brown.edu/individual/jkurtis",
            "name": "Kurtis, Jonathan"
        },
        {
            "group": "Pediatrics",
            "id": "http://vivo.brown.edu/individual/jusanche",
            "name": "Sanchez-Esteban, Juan"
        },
        {
            "group": "Pathology and Laboratory Medicine",
            "id": "http://vivo.brown.edu/individual/asbrodsk",
            "name": "Brodsky, Alexander"
        },
        {
            "group": "Medicine",
            "id": "http://vivo.brown.edu/individual/jaliotta",
            "name": "Aliotta, Jason"
        },
        {
            "group": "Medicine",
            "id": "http://vivo.brown.edu/individual/jwandsmd",
            "name": "Wands, Jack"
        },
        {
            "group": "Health Services, Policy and Practice",
            "id": "http://vivo.brown.edu/individual/zfeng",
            "name": "Feng, Zhanlian"
        },
        {
            "group": "Family Medicine",
            "id": "http://vivo.brown.edu/individual/ceatonmd",
            "name": "Eaton, Charles"
        },
        {
            "group": "Health Services, Policy and Practice",
            "id": "http://vivo.brown.edu/individual/kst",
            "name": "Thomas, Kali"
        },
        {
            "group": "Obstetrics and Gynecology",
            "id": "http://vivo.brown.edu/individual/suvinmd",
            "name": "Cu-Uvin, Susan"
        },
        {
            "group": "Behavioral and Social Sciences",
            "id": "http://vivo.brown.edu/individual/wrakowsk",
            "name": "Rakowski, William"
        },
        {
            "group": "Health Services, Policy and Practice",
            "id": "http://vivo.brown.edu/individual/ddore",
            "name": "Dore, David"
        },
        {
            "group": "Epidemiology",
            "id": "http://vivo.brown.edu/individual/bm8",
            "name": "Marshall, Brandon"
        },
        {
            "group": "Health Services, Policy and Practice",
            "id": "http://vivo.brown.edu/individual/sallen",
            "name": "Allen, Susan"
        },
        {
            "group": "Epidemiology",
            "id": "http://vivo.brown.edu/individual/gwelleni",
            "name": "Wellenius, Gregory"
        },
        {
            "group": "Epidemiology",
            "id": "http://vivo.brown.edu/individual/smcgarve",
            "name": "McGarvey, Stephen"
        },
        {
            "group": "Biostatistics",
            "id": "http://vivo.brown.edu/individual/tl7",
            "name": "Liu, Tao"
        },
        {
            "group": "Pediatrics",
            "id": "http://vivo.brown.edu/individual/auzun",
            "name": "Uzun, Alper"
        },
        {
            "group": "Medicine",
            "id": "http://vivo.brown.edu/individual/atuya",
            "name": "Fulton, Ana"
        },
        {
            "group": "Health Services, Policy and Practice",
            "id": "http://vivo.brown.edu/individual/smillerp",
            "name": "Miller, Susan"
        },
        {
            "group": "Pediatrics",
            "id": "http://vivo.brown.edu/individual/sc7",
            "name": "Cheng, Shibin"
        },
        {
            "group": "Medicine",
            "id": "http://vivo.brown.edu/individual/atrivedi",
            "name": "Trivedi, Amal"
        },
        {
            "group": "Psychiatry and Human Behavior",
            "id": "http://vivo.brown.edu/individual/vknopik",
            "name": "Knopik, Valerie"
        },
        {
            "group": "Psychiatry and Human Behavior",
            "id": "http://vivo.brown.edu/individual/lstroud",
            "name": "Stroud, Laura"
        },
        {
            "group": "Health Services, Policy and Practice",
            "id": "http://vivo.brown.edu/individual/bgenberg",
            "name": "Genberg, Becky"
        },
        {
            "group": "Sociology",
            "id": "http://vivo.brown.edu/individual/miwhite",
            "name": "White, Michael"
        },
        {
            "group": "Psychiatry and Human Behavior",
            "id": "http://vivo.brown.edu/individual/rswiftmd",
            "name": "Swift, Robert"
        },
        {
            "group": "Biostatistics",
            "id": "http://vivo.brown.edu/individual/rg5",
            "name": "Gutman, Roee"
        },
        {
            "group": "Surgery",
            "id": "http://vivo.brown.edu/individual/mvezerid",
            "name": "Vezeridis, Michael"
        },
        {
            "group": "Health Services, Policy and Practice",
            "id": "http://vivo.brown.edu/individual/lresnikp",
            "name": "Resnik, Linda"
        },
        {
            "group": "Ecology and Evolutionary Biology",
            "id": "http://vivo.brown.edu/individual/ks18",
            "name": "Smith, Katherine"
        },
        {
            "group": "Epidemiology",
            "id": "http://vivo.brown.edu/individual/eloucks",
            "name": "Loucks, Eric"
        },
        {
            "group": "Surgery",
            "id": "http://vivo.brown.edu/individual/aayalaph",
            "name": "Ayala, Alfred"
        },
        {
            "group": "Medicine",
            "id": "http://vivo.brown.edu/individual/ejcarter",
            "name": "Carter, E."
        },
        {
            "group": "Pathology and Laboratory Medicine",
            "id": "http://vivo.brown.edu/individual/skostadi",
            "name": "Kostadinov, Stefan"
        },
        {
            "group": "Medicine",
            "id": "http://vivo.brown.edu/individual/rbesdine",
            "name": "Besdine, Richard"
        },
        {
            "group": "Molecular Biology, Cell Biology and Biochemistry",
            "id": "http://vivo.brown.edu/individual/shaley",
            "name": "Haley, Sheila"
        },
        {
            "group": "Pathology and Laboratory Medicine",
            "id": "http://vivo.brown.edu/individual/draj1",
            "name": "Raj, Dipak"
        },
        {
            "group": "Behavioral and Social Sciences",
            "id": "http://vivo.brown.edu/individual/dmwillia",
            "name": "Williams, David"
        },
        {
            "group": "Psychiatry and Human Behavior",
            "id": "http://vivo.brown.edu/individual/bbockphd",
            "name": "Bock, Beth"
        },
        {
            "group": "Biostatistics",
            "id": "http://vivo.brown.edu/individual/xl6",
            "name": "Luo, Xi"
        },
        {
            "group": "Pediatrics",
            "id": "http://vivo.brown.edu/individual/khawes",
            "name": "Hawes, Katheleen"
        },
        {
            "group": "Pediatrics",
            "id": "http://vivo.brown.edu/individual/imichelo",
            "name": "Michelow, Ian"
        },
        {
            "group": "Psychiatry and Human Behavior",
            "id": "http://vivo.brown.edu/individual/rpapas",
            "name": "Papas, Rebecca"
        },
        {
            "group": "Biostatistics",
            "id": "http://vivo.brown.edu/individual/zjwu",
            "name": "Wu, Zhijin"
        },
        {
            "group": "Surgery",
            "id": "http://vivo.brown.edu/individual/fluksmd",
            "name": "Luks, Francois"
        },
        {
            "group": "Biostatistics",
            "id": "http://vivo.brown.edu/individual/gpapando",
            "name": "Papandonatos, George"
        },
        {
            "group": "Epidemiology",
            "id": "http://vivo.brown.edu/individual/agjelsvi",
            "name": "Gjelsvik, Annie"
        },
        {
            "group": "Pathology and Laboratory Medicine",
            "id": "http://vivo.brown.edu/individual/fgundoga",
            "name": "Gundogan, Fusun"
        },
        {
            "group": "Sociology",
            "id": "http://vivo.brown.edu/individual/mfennell",
            "name": "Fennell, Mary"
        },
        {
            "group": "Pathology and Laboratory Medicine",
            "id": "http://vivo.brown.edu/individual/ktkelsey",
            "name": "Kelsey, Karl"
        },
        {
            "group": "Health Services, Policy and Practice",
            "id": "http://vivo.brown.edu/individual/ogalarra",
            "name": "Galarraga, Omar"
        },
        {
            "group": "Pathology and Laboratory Medicine",
            "id": "http://vivo.brown.edu/individual/gpalomak",
            "name": "Palomaki, Glenn"
        },
        {
            "group": "Community Health",
            "id": "http://vivo.brown.edu/individual/sbuka",
            "name": "Buka, Stephen"
        },
        {
            "group": "Behavioral and Social Sciences",
            "id": "http://vivo.brown.edu/individual/rrosen",
            "name": "Rosen, Rochelle"
        },
        {
            "group": "Gerontology and Health Care Research",
            "id": "http://vivo.brown.edu/individual/rbaier",
            "name": "Baier, Rosa"
        },
        {
            "group": "Pediatrics",
            "id": "http://vivo.brown.edu/individual/pgruppus",
            "name": "Gruppuso, Philip"
        },
        {
            "group": "Health Services, Policy and Practice",
            "id": "http://vivo.brown.edu/individual/twetle",
            "name": "Wetle, Terrie"
        },
        {
            "group": "Health Services, Policy and Practice",
            "id": "http://vivo.brown.edu/individual/vmor",
            "name": "Mor, Vincent"
        },
        {
            "group": "Health Services, Policy and Practice",
            "id": "http://vivo.brown.edu/individual/rshieldp",
            "name": "Shield, Renee"
        },
        {
            "group": "Pediatrics",
            "id": "http://vivo.brown.edu/individual/skshaw",
            "name": "Shaw, Sunil"
        },
        {
            "group": "Medicine",
            "id": "http://vivo.brown.edu/individual/rkantor",
            "name": "Kantor, Rami"
        },
        {
            "group": "Medicine",
            "id": "http://vivo.brown.edu/individual/nwardmd",
            "name": "Ward, Nicholas"
        },
        {
            "group": "Psychiatry and Human Behavior",
            "id": "http://vivo.brown.edu/individual/aspirito",
            "name": "Spirito, Anthony"
        },
        {
            "group": "Molecular Biology, Cell Biology and Biochemistry",
            "id": "http://vivo.brown.edu/individual/cschorlp",
            "name": "Schorl, Christoph"
        },
        {
            "group": "Health Services, Policy and Practice",
            "id": "http://vivo.brown.edu/individual/mrahman",
            "name": "Rahman, Md"
        },
        {
            "group": "Pediatrics",
            "id": "http://vivo.brown.edu/individual/bstonest",
            "name": "Stonestreet, Barbara"
        },
        {
            "group": "Medicine",
            "id": "http://vivo.brown.edu/individual/sgravens",
            "name": "Gravenstein, Stefan"
        },
        {
            "group": "Pathology and Laboratory Medicine",
            "id": "http://vivo.brown.edu/individual/estopamd",
            "name": "Stopa, Edward"
        },
        {
            "group": "Medicine",
            "id": "http://vivo.brown.edu/individual/fgillani",
            "name": "Gillani, Fizza"
        },
        {
            "group": "Pediatrics",
            "id": "http://vivo.brown.edu/individual/jbliss",
            "name": "Bliss, Joseph"
        },
        {
            "group": "Emergency Medicine",
            "id": "http://vivo.brown.edu/individual/rcmercha",
            "name": "Merchant, Roland"
        },
        {
            "group": "Medicine",
            "id": "http://vivo.brown.edu/individual/wcwu",
            "name": "Wu, Wen-Chih"
        },
        {
            "group": "Health Services, Policy and Practice",
            "id": "http://vivo.brown.edu/individual/eamiller",
            "name": "Miller, Edward"
        },
        {
            "group": "Behavioral and Social Sciences",
            "id": "http://vivo.brown.edu/individual/nbarnett",
            "name": "Barnett, Nancy"
        },
        {
            "group": "Psychiatry and Human Behavior",
            "id": "http://vivo.brown.edu/individual/rnjones",
            "name": "Jones, Rich"
        },
        {
            "group": "Health Services, Policy and Practice",
            "id": "http://vivo.brown.edu/individual/pgozalo",
            "name": "Gozalo, Pedro"
        },
        {
            "group": "Pediatrics",
            "id": "http://vivo.brown.edu/individual/jpadbury",
            "name": "Padbury, James"
        },
        {
            "group": "Pediatrics",
            "id": "http://vivo.brown.edu/individual/jffriedm",
            "name": "Friedman, Jennifer"
        },
        {
            "group": "Medicine",
            "id": "http://vivo.brown.edu/individual/iwilson",
            "name": "Wilson, Ira"
        },
        {
            "group": "Pathology and Laboratory Medicine",
            "id": "http://vivo.brown.edu/individual/cnixon",
            "name": "Nixon, Christian"
        },
        {
            "group": "Pediatrics",
            "id": "http://vivo.brown.edu/individual/asalisbu",
            "name": "Salisbury, Amy"
        },
        {
            "group": "Obstetrics and Gynecology",
            "id": "http://vivo.brown.edu/individual/dcoustan",
            "name": "Coustan, Donald"
        },
        {
            "group": "Medicine",
            "id": "http://vivo.brown.edu/individual/jrichmph",
            "name": "Rich, Josiah"
        }
    ]
}