{
    "directed": false,
    "graph": {
        "name": "compose( ,  )"
    },
    "links": [
        {
            "source": "http://vivo.brown.edu/individual/mvantwou",
            "target": "http://vivo.brown.edu/individual/jbarredo",
            "weight": 1
        },
        {
            "source": "http://vivo.brown.edu/individual/scruiksh",
            "target": "http://vivo.brown.edu/individual/anurmikk",
            "weight": 1
        },
        {
            "source": "http://vivo.brown.edu/individual/scruiksh",
            "target": "http://vivo.brown.edu/individual/bconnors",
            "weight": 11
        },
        {
            "source": "http://vivo.brown.edu/individual/cvargas",
            "target": "http://vivo.brown.edu/individual/anurmikk",
            "weight": 1
        },
        {
            "source": "http://vivo.brown.edu/individual/mtatarph",
            "target": "http://vivo.brown.edu/individual/jsedivy",
            "weight": 2
        },
        {
            "source": "http://vivo.brown.edu/individual/jasander",
            "target": "http://vivo.brown.edu/individual/jsedivy",
            "weight": 2
        },
        {
            "source": "http://vivo.brown.edu/individual/sw30",
            "target": "http://vivo.brown.edu/individual/jsedivy",
            "weight": 1
        },
        {
            "source": "http://vivo.brown.edu/individual/jkreilin",
            "target": "http://vivo.brown.edu/individual/jsedivy",
            "weight": 4
        },
        {
            "source": "http://vivo.brown.edu/individual/jsedivy",
            "target": "http://vivo.brown.edu/individual/kboekelh",
            "weight": 3
        },
        {
            "source": "http://vivo.brown.edu/individual/jsedivy",
            "target": "http://vivo.brown.edu/individual/watwoodp",
            "weight": 2
        },
        {
            "source": "http://vivo.brown.edu/individual/jsedivy",
            "target": "http://vivo.brown.edu/individual/mkimmd",
            "weight": 1
        },
        {
            "source": "http://vivo.brown.edu/individual/jsedivy",
            "target": "http://vivo.brown.edu/individual/jwandsmd",
            "weight": 1
        },
        {
            "source": "http://vivo.brown.edu/individual/jsedivy",
            "target": "http://vivo.brown.edu/individual/arsalomo",
            "weight": 1
        },
        {
            "source": "http://vivo.brown.edu/individual/jsedivy",
            "target": "http://vivo.brown.edu/individual/smossmd",
            "weight": 1
        },
        {
            "source": "http://vivo.brown.edu/individual/jsedivy",
            "target": "http://vivo.brown.edu/individual/nneretti",
            "weight": 11
        },
        {
            "source": "http://vivo.brown.edu/individual/jsedivy",
            "target": "http://vivo.brown.edu/individual/pgruppus",
            "weight": 2
        },
        {
            "source": "http://vivo.brown.edu/individual/jsedivy",
            "target": "http://vivo.brown.edu/individual/rburwell",
            "weight": 1
        },
        {
            "source": "http://vivo.brown.edu/individual/jsedivy",
            "target": "http://vivo.brown.edu/individual/cschorlp",
            "weight": 4
        },
        {
            "source": "http://vivo.brown.edu/individual/jsimeral",
            "target": "http://vivo.brown.edu/individual/bconnors",
            "weight": 1
        },
        {
            "source": "http://vivo.brown.edu/individual/tserre",
            "target": "http://vivo.brown.edu/individual/dsheinbe",
            "weight": 1
        },
        {
            "source": "http://vivo.brown.edu/individual/nphilip",
            "target": "http://vivo.brown.edu/individual/jbarredo",
            "weight": 1
        },
        {
            "source": "http://vivo.brown.edu/individual/anurmikk",
            "target": "http://vivo.brown.edu/individual/lhochber",
            "weight": 1
        },
        {
            "source": "http://vivo.brown.edu/individual/anurmikk",
            "target": "http://vivo.brown.edu/individual/rburwell",
            "weight": 2
        },
        {
            "source": "http://vivo.brown.edu/individual/anurmikk",
            "target": "http://vivo.brown.edu/individual/ll7",
            "weight": 1
        },
        {
            "source": "http://vivo.brown.edu/individual/anurmikk",
            "target": "http://vivo.brown.edu/individual/dsheinbe",
            "weight": 3
        },
        {
            "source": "http://vivo.brown.edu/individual/anurmikk",
            "target": "http://vivo.brown.edu/individual/jdonoghu",
            "weight": 3
        },
        {
            "source": "http://vivo.brown.edu/individual/anurmikk",
            "target": "http://vivo.brown.edu/individual/rzia",
            "weight": 1
        },
        {
            "source": "http://vivo.brown.edu/individual/anurmikk",
            "target": "http://vivo.brown.edu/individual/dborton",
            "weight": 9
        },
        {
            "source": "http://vivo.brown.edu/individual/anurmikk",
            "target": "http://vivo.brown.edu/individual/bconnors",
            "weight": 2
        },
        {
            "source": "http://vivo.brown.edu/individual/rburwell",
            "target": "http://vivo.brown.edu/individual/dborton",
            "weight": 3
        },
        {
            "source": "http://vivo.brown.edu/individual/rburwell",
            "target": "http://vivo.brown.edu/individual/kscaplen",
            "weight": 1
        },
        {
            "source": "http://vivo.brown.edu/individual/rburwell",
            "target": "http://vivo.brown.edu/individual/bconnors",
            "weight": 3
        },
        {
            "source": "http://vivo.brown.edu/individual/rburwell",
            "target": "http://vivo.brown.edu/individual/jbarredo",
            "weight": 1
        },
        {
            "source": "http://vivo.brown.edu/individual/rburwell",
            "target": "http://vivo.brown.edu/individual/dsheinbe",
            "weight": 1
        },
        {
            "source": "http://vivo.brown.edu/individual/mtharris",
            "target": "http://vivo.brown.edu/individual/dsheinbe",
            "weight": 3
        },
        {
            "source": "http://vivo.brown.edu/individual/lhochber",
            "target": "http://vivo.brown.edu/individual/dborton",
            "weight": 1
        },
        {
            "source": "http://vivo.brown.edu/individual/ll7",
            "target": "http://vivo.brown.edu/individual/dborton",
            "weight": 1
        },
        {
            "source": "http://vivo.brown.edu/individual/bconnors",
            "target": "http://vivo.brown.edu/individual/jmachan",
            "weight": 1
        },
        {
            "source": "http://vivo.brown.edu/individual/dborton",
            "target": "http://vivo.brown.edu/individual/jdonoghu",
            "weight": 2
        },
        {
            "source": "http://vivo.brown.edu/individual/dborton",
            "target": "http://vivo.brown.edu/individual/dsheinbe",
            "weight": 2
        }
    ],
    "multigraph": false,
    "nodes": [
        {
            "group": "Psychiatry and Human Behavior",
            "id": "http://vivo.brown.edu/individual/mvantwou",
            "name": "van 't Wout, Mascha"
        },
        {
            "group": "Neuroscience",
            "id": "http://vivo.brown.edu/individual/scruiksh",
            "name": "Cruikshank, Scott"
        },
        {
            "group": "Neuroscience",
            "id": "http://vivo.brown.edu/individual/cvargas",
            "name": "Vargas-Irwin, Carlos"
        },
        {
            "group": "Ecology and Evolutionary Biology",
            "id": "http://vivo.brown.edu/individual/mtatarph",
            "name": "Tatar, Marc"
        },
        {
            "group": "Pediatrics",
            "id": "http://vivo.brown.edu/individual/jasander",
            "name": "Sanders, Jennifer"
        },
        {
            "group": "Medicine",
            "id": "http://vivo.brown.edu/individual/sw30",
            "name": "Wen, Sicheng"
        },
        {
            "group": "Molecular Biology, Cell Biology and Biochemistry",
            "id": "http://vivo.brown.edu/individual/jkreilin",
            "name": "Kreiling, Jill"
        },
        {
            "group": "Molecular Biology, Cell Biology and Biochemistry",
            "id": "http://vivo.brown.edu/individual/jsedivy",
            "name": "Sedivy, John"
        },
        {
            "group": "Engineering",
            "id": "http://vivo.brown.edu/individual/jsimeral",
            "name": "Simeral, John"
        },
        {
            "group": "Molecular Biology, Cell Biology and Biochemistry",
            "id": "http://vivo.brown.edu/individual/nneretti",
            "name": "Neretti, Nicola"
        },
        {
            "group": "Chemistry",
            "id": "http://vivo.brown.edu/individual/arsalomo",
            "name": "Salomon, Arthur"
        },
        {
            "group": "Cognitive, Linguistic and Psychological Sciences",
            "id": "http://vivo.brown.edu/individual/tserre",
            "name": "Serre, Thomas"
        },
        {
            "group": "Psychiatry and Human Behavior",
            "id": "http://vivo.brown.edu/individual/nphilip",
            "name": "Philip, Noah"
        },
        {
            "group": "Physics",
            "id": "http://vivo.brown.edu/individual/anurmikk",
            "name": "Nurmikko, Arto"
        },
        {
            "group": "Psychology",
            "id": "http://vivo.brown.edu/individual/rburwell",
            "name": "Burwell, Rebecca"
        },
        {
            "group": "Applied Mathematics",
            "id": "http://vivo.brown.edu/individual/mtharris",
            "name": "Harrison, Matthew"
        },
        {
            "group": "Psychiatry and Human Behavior",
            "id": "http://vivo.brown.edu/individual/jbarredo",
            "name": "Barredo, Jennifer"
        },
        {
            "group": "Engineering",
            "id": "http://vivo.brown.edu/individual/lhochber",
            "name": "Hochberg, Leigh"
        },
        {
            "group": "Pathology and Laboratory Medicine",
            "id": "http://vivo.brown.edu/individual/kboekelh",
            "name": "Boekelheide, Kim"
        },
        {
            "group": "Engineering",
            "id": "http://vivo.brown.edu/individual/ll7",
            "name": "Larson, Lawrence"
        },
        {
            "group": "Neuroscience",
            "id": "http://vivo.brown.edu/individual/bconnors",
            "name": "Connors, Barry"
        },
        {
            "group": "Neuroscience",
            "id": "http://vivo.brown.edu/individual/kscaplen",
            "name": "Scaplen, Kristin"
        },
        {
            "group": "Medicine",
            "id": "http://vivo.brown.edu/individual/mkimmd",
            "name": "Kim, Miran"
        },
        {
            "group": "Engineering",
            "id": "http://vivo.brown.edu/individual/dborton",
            "name": "Borton, David"
        },
        {
            "group": "Molecular Biology, Cell Biology and Biochemistry",
            "id": "http://vivo.brown.edu/individual/cschorlp",
            "name": "Schorl, Christoph"
        },
        {
            "group": "Pediatrics",
            "id": "http://vivo.brown.edu/individual/pgruppus",
            "name": "Gruppuso, Philip"
        },
        {
            "group": "Medicine",
            "id": "http://vivo.brown.edu/individual/jwandsmd",
            "name": "Wands, Jack"
        },
        {
            "group": "Molecular Biology, Cell Biology and Biochemistry",
            "id": "http://vivo.brown.edu/individual/watwoodp",
            "name": "Atwood, Walter"
        },
        {
            "group": "Medicine",
            "id": "http://vivo.brown.edu/individual/smossmd",
            "name": "Moss, Steven"
        },
        {
            "group": "Orthopaedics",
            "id": "http://vivo.brown.edu/individual/jmachan",
            "name": "Machan, Jason"
        },
        {
            "group": "Engineering",
            "id": "http://vivo.brown.edu/individual/jdonoghu",
            "name": "Donoghue, John"
        },
        {
            "group": "Physics",
            "id": "http://vivo.brown.edu/individual/rzia",
            "name": "Zia, Rashid"
        },
        {
            "group": "Neuroscience",
            "id": "http://vivo.brown.edu/individual/dsheinbe",
            "name": "Sheinberg, David"
        }
    ]
}